[
  { "id": 1, "nom": "Lola", "prenom": "Rakoto", "diplome": "MASTER", "categorie": "Informatique", "sousCategorie": "Développement Web", "payment": "Payé", "date": "15/10/2023" },
  { "id": 2, "nom": "Ayna", "prenom": "Bageda", "diplome": "LICENCE", "categorie": "Marketing", "sousCategorie": "Marketing Digital", "payment": "En attente", "date": "14/10/2023" },
  { "id": 3, "nom": "Kennedy", "prenom": "Votavo", "diplome": "BACC", "categorie": "Commerce", "sousCategorie": "Commerce International", "payment": "Payé", "date": "14/10/2023" },
  { "id": 4, "nom": "Bernard", "prenom": "Lucas", "diplome": "MASTER", "categorie": "Droit", "sousCategorie": "Droit des Affaires", "payment": "Payé", "date": "13/10/2023" },
  { "id": 5, "nom": "Petit", "prenom": "Leo", "diplome": "LICENCE", "categorie": "Communication", "sousCategorie": "Relations Publiques", "payment": "En attente", "date": "12/10/2023" },
  { "id": 6, "nom": "Moreau", "prenom": "Hugo", "diplome": "BEPC", "categorie": "Administration", "sousCategorie": "Secrétariat", "payment": "Payé", "date": "11/10/2023" },
  { "id": 7, "nom": "Roux", "prenom": "Chloé", "diplome": "MASTER", "categorie": "Finance", "sousCategorie": "Comptabilité", "payment": "Payé", "date": "10/10/2023" },
  { "id": 8, "nom": "Vincent", "prenom": "Louis", "diplome": "LICENCE", "categorie": "Ressources Humaines", "sousCategorie": "Recrutement", "payment": "En attente", "date": "09/10/2023" },
  { "id": 9, "nom": "Vincent", "prenom": "Louis", "diplome": "LICENCE", "categorie": "Ressources Humaines", "sousCategorie": "Recrutement", "payment": "En attente", "date": "09/10/2023" },
  { "id": 10, "nom": "Vincent", "prenom": "Louis", "diplome": "LICENCE", "categorie": "Ressources Humaines", "sousCategorie": "Recrutement", "payment": "En attente", "date": "09/10/2023" },
  { "id": 11, "nom": "Vincent", "prenom": "Louis", "diplome": "LICENCE", "categorie": "Ressources Humaines", "sousCategorie": "Recrutement", "payment": "En attente", "date": "09/10/2023" },
  { "id": 12, "nom": "Vincent", "prenom": "Louis", "diplome": "LICENCE", "categorie": "Ressources Humaines", "sousCategorie": "Recrutement", "payment": "En attente", "date": "09/10/2023" }
]
